{
  "update_counts": [
    {
      "key": "ada",
      "value": 35
    },
    {
      "key": "agda",
      "value": 32
    },
    {
      "key": "angular",
      "value": 47
    },
    {
      "key": "apex",
      "value": 48
    },
    {
      "key": "arduino",
      "value": 35
    },
    {
      "key": "asm",
      "value": 33
    },
    {
      "key": "astro",
      "value": 34
    },
    {
      "key": "authzed",
      "value": 30
    },
    {
      "key": "awk",
      "value": 32
    },
    {
      "key": "bash",
      "value": 50
    },
    {
      "key": "bass",
      "value": 30
    },
    {
      "key": "beancount",
      "value": 37
    },
    {
      "key": "bibtex",
      "value": 32
    },
    {
      "key": "bicep",
      "value": 30
    },
    {
      "key": "bitbake",
      "value": 31
    },
    {
      "key": "blueprint",
      "value": 31
    },
    {
      "key": "bp",
      "value": 31
    },
    {
      "key": "c",
      "value": 47
    },
    {
      "key": "c_sharp",
      "value": 48
    },
    {
      "key": "cairo",
      "value": 29
    },
    {
      "key": "capnp",
      "value": 29
    },
    {
      "key": "chatito",
      "value": 33
    },
    {
      "key": "clojure",
      "value": 32
    },
    {
      "key": "cmake",
      "value": 40
    },
    {
      "key": "comment",
      "value": 33
    },
    {
      "key": "commonlisp",
      "value": 30
    },
    {
      "key": "cooklang",
      "value": 29
    },
    {
      "key": "corn",
      "value": 29
    },
    {
      "key": "cpon",
      "value": 29
    },
    {
      "key": "cpp",
      "value": 49
    },
    {
      "key": "css",
      "value": 39
    },
    {
      "key": "csv",
      "value": 30
    },
    {
      "key": "cuda",
      "value": 32
    },
    {
      "key": "cue",
      "value": 30
    },
    {
      "key": "d",
      "value": 36
    },
    {
      "key": "dart",
      "value": 38
    },
    {
      "key": "devicetree",
      "value": 34
    },
    {
      "key": "dhall",
      "value": 35
    },
    {
      "key": "diff",
      "value": 33
    },
    {
      "key": "disassembly",
      "value": 29
    },
    {
      "key": "djot",
      "value": 36
    },
    {
      "key": "dockerfile",
      "value": 30
    },
    {
      "key": "dot",
      "value": 32
    },
    {
      "key": "doxygen",
      "value": 29
    },
    {
      "key": "dtd",
      "value": 41
    },
    {
      "key": "earthfile",
      "value": 40
    },
    {
      "key": "ebnf",
      "value": 29
    },
    {
      "key": "ecma",
      "value": 33
    },
    {
      "key": "editorconfig",
      "value": 68
    },
    {
      "key": "eds",
      "value": 30
    },
    {
      "key": "eex",
      "value": 29
    },
    {
      "key": "elixir",
      "value": 43
    },
    {
      "key": "elm",
      "value": 38
    },
    {
      "key": "elsa",
      "value": 29
    },
    {
      "key": "elvish",
      "value": 29
    },
    {
      "key": "embedded_template",
      "value": 36
    },
    {
      "key": "erlang",
      "value": 49
    },
    {
      "key": "facility",
      "value": 30
    },
    {
      "key": "faust",
      "value": 31
    },
    {
      "key": "fennel",
      "value": 37
    },
    {
      "key": "fidl",
      "value": 29
    },
    {
      "key": "firrtl",
      "value": 29
    },
    {
      "key": "fish",
      "value": 33
    },
    {
      "key": "foam",
      "value": 31
    },
    {
      "key": "forth",
      "value": 30
    },
    {
      "key": "fortran",
      "value": 55
    },
    {
      "key": "fsh",
      "value": 29
    },
    {
      "key": "func",
      "value": 29
    },
    {
      "key": "fusion",
      "value": 30
    },
    {
      "key": "gdscript",
      "value": 46
    },
    {
      "key": "gdshader",
      "value": 38
    },
    {
      "key": "git_config",
      "value": 31
    },
    {
      "key": "git_rebase",
      "value": 29
    },
    {
      "key": "gitattributes",
      "value": 32
    },
    {
      "key": "gitcommit",
      "value": 34
    },
    {
      "key": "gitignore",
      "value": 29
    },
    {
      "key": "gleam",
      "value": 50
    },
    {
      "key": "glimmer",
      "value": 31
    },
    {
      "key": "glsl",
      "value": 31
    },
    {
      "key": "gn",
      "value": 29
    },
    {
      "key": "gnuplot",
      "value": 30
    },
    {
      "key": "go",
      "value": 43
    },
    {
      "key": "goctl",
      "value": 29
    },
    {
      "key": "godot_resource",
      "value": 36
    },
    {
      "key": "gomod",
      "value": 35
    },
    {
      "key": "gosum",
      "value": 30
    },
    {
      "key": "gotmpl",
      "value": 42
    },
    {
      "key": "gowork",
      "value": 29
    },
    {
      "key": "gpg",
      "value": 32
    },
    {
      "key": "graphql",
      "value": 29
    },
    {
      "key": "groovy",
      "value": 34
    },
    {
      "key": "gstlaunch",
      "value": 29
    },
    {
      "key": "hack",
      "value": 32
    },
    {
      "key": "hare",
      "value": 30
    },
    {
      "key": "haskell",
      "value": 40
    },
    {
      "key": "haskell_persistent",
      "value": 29
    },
    {
      "key": "hcl",
      "value": 35
    },
    {
      "key": "heex",
      "value": 36
    },
    {
      "key": "helm",
      "value": 41
    },
    {
      "key": "hjson",
      "value": 29
    },
    {
      "key": "hlsl",
      "value": 32
    },
    {
      "key": "hlsplaylist",
      "value": 29
    },
    {
      "key": "hocon",
      "value": 29
    },
    {
      "key": "hoon",
      "value": 32
    },
    {
      "key": "html",
      "value": 40
    },
    {
      "key": "html_tags",
      "value": 30
    },
    {
      "key": "htmldjango",
      "value": 30
    },
    {
      "key": "http",
      "value": 37
    },
    {
      "key": "hurl",
      "value": 32
    },
    {
      "key": "hyprlang",
      "value": 40
    },
    {
      "key": "idl",
      "value": 42
    },
    {
      "key": "ini",
      "value": 35
    },
    {
      "key": "inko",
      "value": 54
    },
    {
      "key": "ispc",
      "value": 30
    },
    {
      "key": "janet_simple",
      "value": 35
    },
    {
      "key": "java",
      "value": 46
    },
    {
      "key": "javascript",
      "value": 41
    },
    {
      "key": "jq",
      "value": 30
    },
    {
      "key": "jsdoc",
      "value": 36
    },
    {
      "key": "json",
      "value": 40
    },
    {
      "key": "json5",
      "value": 32
    },
    {
      "key": "jsonc",
      "value": 30
    },
    {
      "key": "jsonnet",
      "value": 29
    },
    {
      "key": "jsx",
      "value": 30
    },
    {
      "key": "julia",
      "value": 50
    },
    {
      "key": "just",
      "value": 38
    },
    {
      "key": "kconfig",
      "value": 32
    },
    {
      "key": "kdl",
      "value": 30
    },
    {
      "key": "kotlin",
      "value": 34
    },
    {
      "key": "koto",
      "value": 51
    },
    {
      "key": "kusto",
      "value": 29
    },
    {
      "key": "lalrpop",
      "value": 33
    },
    {
      "key": "latex",
      "value": 41
    },
    {
      "key": "ledger",
      "value": 35
    },
    {
      "key": "leo",
      "value": 33
    },
    {
      "key": "linkerscript",
      "value": 29
    },
    {
      "key": "liquid",
      "value": 34
    },
    {
      "key": "liquidsoap",
      "value": 34
    },
    {
      "key": "llvm",
      "value": 36
    },
    {
      "key": "lua",
      "value": 41
    },
    {
      "key": "luadoc",
      "value": 30
    },
    {
      "key": "luap",
      "value": 29
    },
    {
      "key": "luau",
      "value": 30
    },
    {
      "key": "m68k",
      "value": 29
    },
    {
      "key": "make",
      "value": 32
    },
    {
      "key": "markdown",
      "value": 47
    },
    {
      "key": "markdown_inline",
      "value": 45
    },
    {
      "key": "matlab",
      "value": 53
    },
    {
      "key": "menhir",
      "value": 29
    },
    {
      "key": "mermaid",
      "value": 30
    },
    {
      "key": "meson",
      "value": 43
    },
    {
      "key": "mlir",
      "value": 91
    },
    {
      "key": "muttrc",
      "value": 29
    },
    {
      "key": "nasm",
      "value": 30
    },
    {
      "key": "nginx",
      "value": 31
    },
    {
      "key": "nickel",
      "value": 34
    },
    {
      "key": "nim",
      "value": 32
    },
    {
      "key": "nim_format_string",
      "value": 29
    },
    {
      "key": "ninja",
      "value": 30
    },
    {
      "key": "nix",
      "value": 70
    },
    {
      "key": "nqc",
      "value": 30
    },
    {
      "key": "objc",
      "value": 31
    },
    {
      "key": "objdump",
      "value": 29
    },
    {
      "key": "ocaml",
      "value": 46
    },
    {
      "key": "ocaml_interface",
      "value": 47
    },
    {
      "key": "ocamllex",
      "value": 33
    },
    {
      "key": "odin",
      "value": 32
    },
    {
      "key": "org",
      "value": 2
    },
    {
      "key": "pascal",
      "value": 34
    },
    {
      "key": "passwd",
      "value": 29
    },
    {
      "key": "pem",
      "value": 32
    },
    {
      "key": "perl",
      "value": 48
    },
    {
      "key": "php",
      "value": 51
    },
    {
      "key": "php_only",
      "value": 55
    },
    {
      "key": "phpdoc",
      "value": 33
    },
    {
      "key": "pioasm",
      "value": 30
    },
    {
      "key": "po",
      "value": 29
    },
    {
      "key": "pod",
      "value": 29
    },
    {
      "key": "poe_filter",
      "value": 33
    },
    {
      "key": "pony",
      "value": 30
    },
    {
      "key": "printf",
      "value": 33
    },
    {
      "key": "prisma",
      "value": 31
    },
    {
      "key": "problog",
      "value": 31
    },
    {
      "key": "prolog",
      "value": 31
    },
    {
      "key": "promql",
      "value": 30
    },
    {
      "key": "properties",
      "value": 32
    },
    {
      "key": "proto",
      "value": 30
    },
    {
      "key": "prql",
      "value": 31
    },
    {
      "key": "psv",
      "value": 30
    },
    {
      "key": "pug",
      "value": 30
    },
    {
      "key": "puppet",
      "value": 30
    },
    {
      "key": "purescript",
      "value": 34
    },
    {
      "key": "pymanifest",
      "value": 30
    },
    {
      "key": "python",
      "value": 56
    },
    {
      "key": "ql",
      "value": 31
    },
    {
      "key": "qmldir",
      "value": 29
    },
    {
      "key": "qmljs",
      "value": 33
    },
    {
      "key": "query",
      "value": 48
    },
    {
      "key": "r",
      "value": 39
    },
    {
      "key": "racket",
      "value": 36
    },
    {
      "key": "ralph",
      "value": 29
    },
    {
      "key": "rasi",
      "value": 30
    },
    {
      "key": "rbs",
      "value": 33
    },
    {
      "key": "re2c",
      "value": 32
    },
    {
      "key": "readline",
      "value": 31
    },
    {
      "key": "regex",
      "value": 41
    },
    {
      "key": "rego",
      "value": 30
    },
    {
      "key": "requirements",
      "value": 31
    },
    {
      "key": "rnoweb",
      "value": 29
    },
    {
      "key": "robot",
      "value": 33
    },
    {
      "key": "robots",
      "value": 30
    },
    {
      "key": "roc",
      "value": 40
    },
    {
      "key": "ron",
      "value": 29
    },
    {
      "key": "rst",
      "value": 33
    },
    {
      "key": "ruby",
      "value": 39
    },
    {
      "key": "rust",
      "value": 57
    },
    {
      "key": "scala",
      "value": 55
    },
    {
      "key": "scfg",
      "value": 31
    },
    {
      "key": "scheme",
      "value": 38
    },
    {
      "key": "scss",
      "value": 29
    },
    {
      "key": "slang",
      "value": 36
    },
    {
      "key": "slint",
      "value": 44
    },
    {
      "key": "smali",
      "value": 29
    },
    {
      "key": "smithy",
      "value": 30
    },
    {
      "key": "snakemake",
      "value": 35
    },
    {
      "key": "solidity",
      "value": 38
    },
    {
      "key": "soql",
      "value": 46
    },
    {
      "key": "sosl",
      "value": 44
    },
    {
      "key": "sourcepawn",
      "value": 31
    },
    {
      "key": "sparql",
      "value": 31
    },
    {
      "key": "sql",
      "value": 52
    },
    {
      "key": "squirrel",
      "value": 29
    },
    {
      "key": "ssh_config",
      "value": 34
    },
    {
      "key": "starlark",
      "value": 33
    },
    {
      "key": "strace",
      "value": 31
    },
    {
      "key": "styled",
      "value": 33
    },
    {
      "key": "supercollider",
      "value": 35
    },
    {
      "key": "surface",
      "value": 29
    },
    {
      "key": "svelte",
      "value": 33
    },
    {
      "key": "swift",
      "value": 63
    },
    {
      "key": "sxhkdrc",
      "value": 30
    },
    {
      "key": "systemtap",
      "value": 29
    },
    {
      "key": "systemverilog",
      "value": 45
    },
    {
      "key": "t32",
      "value": 59
    },
    {
      "key": "tablegen",
      "value": 30
    },
    {
      "key": "tact",
      "value": 38
    },
    {
      "key": "tcl",
      "value": 37
    },
    {
      "key": "teal",
      "value": 35
    },
    {
      "key": "templ",
      "value": 56
    },
    {
      "key": "terraform",
      "value": 36
    },
    {
      "key": "textproto",
      "value": 31
    },
    {
      "key": "thrift",
      "value": 30
    },
    {
      "key": "tiger",
      "value": 30
    },
    {
      "key": "tlaplus",
      "value": 39
    },
    {
      "key": "tmux",
      "value": 35
    },
    {
      "key": "todotxt",
      "value": 29
    },
    {
      "key": "toml",
      "value": 31
    },
    {
      "key": "tsv",
      "value": 30
    },
    {
      "key": "tsx",
      "value": 37
    },
    {
      "key": "turtle",
      "value": 29
    },
    {
      "key": "twig",
      "value": 30
    },
    {
      "key": "typescript",
      "value": 38
    },
    {
      "key": "typespec",
      "value": 36
    },
    {
      "key": "typoscript",
      "value": 33
    },
    {
      "key": "typst",
      "value": 38
    },
    {
      "key": "udev",
      "value": 31
    },
    {
      "key": "ungrammar",
      "value": 29
    },
    {
      "key": "unison",
      "value": 35
    },
    {
      "key": "usd",
      "value": 30
    },
    {
      "key": "uxntal",
      "value": 29
    },
    {
      "key": "v",
      "value": 54
    },
    {
      "key": "vala",
      "value": 30
    },
    {
      "key": "vento",
      "value": 30
    },
    {
      "key": "verilog",
      "value": 40
    },
    {
      "key": "vhdl",
      "value": 54
    },
    {
      "key": "vhs",
      "value": 34
    },
    {
      "key": "vim",
      "value": 41
    },
    {
      "key": "vimdoc",
      "value": 39
    },
    {
      "key": "vue",
      "value": 34
    },
    {
      "key": "wgsl",
      "value": 31
    },
    {
      "key": "wgsl_bevy",
      "value": 32
    },
    {
      "key": "wing",
      "value": 29
    },
    {
      "key": "wit",
      "value": 37
    },
    {
      "key": "xcompose",
      "value": 30
    },
    {
      "key": "xml",
      "value": 43
    },
    {
      "key": "yaml",
      "value": 38
    },
    {
      "key": "yang",
      "value": 29
    },
    {
      "key": "yuck",
      "value": 29
    },
    {
      "key": "zathurarc",
      "value": 29
    },
    {
      "key": "zig",
      "value": 37
    },
    {
      "key": "powershell",
      "value": 48
    },
    {
      "key": "rescript",
      "value": 32
    },
    {
      "key": "vrl",
      "value": 29
    },
    {
      "key": "sflog",
      "value": 44
    },
    {
      "key": "gap",
      "value": 34
    },
    {
      "key": "gaptst",
      "value": 30
    },
    {
      "key": "glimmer_javascript",
      "value": 36
    },
    {
      "key": "glimmer_typescript",
      "value": 36
    },
    {
      "key": "fsharp",
      "value": 17
    },
    {
      "key": "ziggy",
      "value": 19
    },
    {
      "key": "ziggy_schema",
      "value": 20
    },
    {
      "key": "superhtml",
      "value": 34
    },
    {
      "key": "gren",
      "value": 7
    },
    {
      "key": "xresources",
      "value": 47
    },
    {
      "key": "desktop",
      "value": 38
    },
    {
      "key": "cylc",
      "value": 5
    },
    {
      "key": "sway",
      "value": 5
    },
    {
      "key": "nu",
      "value": 62
    },
    {
      "key": "runescript",
      "value": 1
    },
    {
      "key": "circom",
      "value": 2
    },
    {
      "key": "ipkg",
      "value": 2
    },
    {
      "key": "idris",
      "value": 1
    },
    {
      "key": "slim",
      "value": 7
    },
    {
      "key": "razor",
      "value": 3
    },
    {
      "key": "enforce",
      "value": 12
    },
    {
      "key": "jinja",
      "value": 11
    },
    {
      "key": "jinja_inline",
      "value": 15
    },
    {
      "key": "kcl",
      "value": 2
    },
    {
      "key": "tera",
      "value": 9
    },
    {
      "key": "blade",
      "value": 8
    },
    {
      "key": "caddy",
      "value": 2
    },
    {
      "key": "javadoc",
      "value": 37
    },
    {
      "key": "brightscript",
      "value": 3
    },
    {
      "key": "c3",
      "value": 14
    },
    {
      "key": "groq",
      "value": 3
    },
    {
      "key": "pkl",
      "value": 13
    },
    {
      "key": "sproto",
      "value": 2
    },
    {
      "key": "wxml",
      "value": 2
    },
    {
      "key": "rifleconf",
      "value": 4
    },
    {
      "key": "snl",
      "value": 2
    },
    {
      "key": "kitty",
      "value": 6
    },
    {
      "key": "kulala_http",
      "value": 1
    },
    {
      "key": "zsh",
      "value": 11
    },
    {
      "key": "robots_txt",
      "value": 2
    },
    {
      "key": "kos",
      "value": 4
    },
    {
      "key": "bpftrace",
      "value": 6
    }
  ]
}
